{"noiseKey":{"private":{"type":"Buffer","data":"2NleRCTfNn2N8Ql3lmCgSwanphZKkiA2xmRg+zeb6Gw="},"public":{"type":"Buffer","data":"QC6TlAi2wXSUD97skj5HcQ+ufxpXSohz9xz+yxwtMmo="}},"pairingEphemeralKeyPair":{"private":{"type":"Buffer","data":"QKosGc8OaV5Z+H9v9L0nZ2JH2jTErJOwmG7F6hX4h1A="},"public":{"type":"Buffer","data":"GZnKlV3rxRJyxZxmfQHgDuT4p/XI0u8yeJ4CI6n4HT8="}},"signedIdentityKey":{"private":{"type":"Buffer","data":"IPUp2SPmlvpIdjPoMHGMlzPjurcT6HJWZXBbNhzT+F0="},"public":{"type":"Buffer","data":"hzOFP9HNvZrfNPbyxUH/mdkdht7KgSI9xna6JgZIKhc="}},"signedPreKey":{"keyPair":{"private":{"type":"Buffer","data":"2MK02i1r+oMmsS8eOc+HOzRYDWEJXHpqz+jr+Ij353M="},"public":{"type":"Buffer","data":"YCTLo+Gq3oYgJ0mgPdHJNAqKpq6T6702XEYb+Ude6gE="}},"signature":{"type":"Buffer","data":"wvjGmYeGoPl1bNDg68fIOsRY76nAy5YIlwt3wzVN3v0psRzS/z9nmoMam1aQXJARNVGWuw8Z8a34JZ7ZFI8pDA=="},"keyId":1},"registrationId":94,"advSecretKey":"rurWG/slgBUEERBI8ShYpWCEXtNE2cDPnT84CZT1fu0=","processedHistoryMessages":[{"key":{"remoteJid":"62895339917334@s.whatsapp.net","fromMe":true,"id":"3AB442193DE2D9918726"},"messageTimestamp":1777274199},{"key":{"remoteJid":"62895339917334@s.whatsapp.net","fromMe":true,"id":"3A80CA3A165EE52EA615"},"messageTimestamp":1777274201},{"key":{"remoteJid":"62895339917334@s.whatsapp.net","fromMe":true,"id":"3A0651E7255EB67C1B9A"},"messageTimestamp":1777274215},{"key":{"remoteJid":"62895339917334@s.whatsapp.net","fromMe":true,"id":"3A2BB6C08FBE8B36554F"},"messageTimestamp":1777274229},{"key":{"remoteJid":"62895339917334@s.whatsapp.net","fromMe":true,"id":"3A6362228180E6A05D25"},"messageTimestamp":1777274237},{"key":{"remoteJid":"62895339917334@s.whatsapp.net","fromMe":true,"id":"3A903D2F559F890A2FF1"},"messageTimestamp":1777274244},{"key":{"remoteJid":"62895339917334@s.whatsapp.net","fromMe":true,"id":"3A4FBF04CFB498460864"},"messageTimestamp":1777274255},{"key":{"remoteJid":"62895339917334@s.whatsapp.net","fromMe":true,"id":"3A840F848680DED72FEC"},"messageTimestamp":1777274255}],"nextPreKeyId":36,"firstUnuploadedPreKeyId":36,"accountSyncCounter":1,"accountSettings":{"unarchiveChats":false},"registered":false,"account":{"details":"CKfc054PEMiavM8GGAYgACgA","accountSignatureKey":"yk37bd/ocPHclon+1nBZXUBiqHhHbUYAA011A8hN62A=","accountSignature":"p4QR603Gvj3LM/1n8aTX01PyhZAyM7X2QWhW1qQ5KGQRgX+L0BGC0d7qWPRbSZzeJ5ZUgisHz00cjy1LM/4EBg==","deviceSignature":"t9TzLSiyZISmosfttX9c0oHhuDvOD3nKtFvWzZNYoQcrR/N9URahO+LYTSq7UOBIpxHcU58QEQ2SSZnqy7TlCA=="},"me":{"id":"62895339917334:15@s.whatsapp.net","lid":"149439259881521:15@lid","name":"luthfi"},"signalIdentities":[{"identifier":{"name":"62895339917334:15@s.whatsapp.net","deviceId":0},"identifierKey":{"type":"Buffer","data":"BcpN+23f6HDx3JaJ/tZwWV1AYqh4R21GAANNdQPITetg"}}],"platform":"iphone","routingInfo":{"type":"Buffer","data":"CBIIBQgI"},"lastAccountSyncTimestamp":1777274280,"myAppStateKeyId":"AAAAAL/v"}